AUTHORS.rst
CONTRIBUTING.rst
HISTORY.rst
LICENSE
MANIFEST.in
README.rst
setup.cfg
setup.py
mozilla_django_oidc/__init__.py
mozilla_django_oidc/auth.py
mozilla_django_oidc/middleware.py
mozilla_django_oidc/urls.py
mozilla_django_oidc/utils.py
mozilla_django_oidc/views.py
mozilla_django_oidc/contrib/__init__.py
mozilla_django_oidc/contrib/drf.py
mozilla_django_oidc_foxtail.egg-info/PKG-INFO
mozilla_django_oidc_foxtail.egg-info/SOURCES.txt
mozilla_django_oidc_foxtail.egg-info/dependency_links.txt
mozilla_django_oidc_foxtail.egg-info/not-zip-safe
mozilla_django_oidc_foxtail.egg-info/requires.txt
mozilla_django_oidc_foxtail.egg-info/top_level.txt